databases/__init__.py
databases/core.py
databases/importer.py
databases/interfaces.py
databases/py.typed
databases/backends/__init__.py
databases/backends/aiopg.py
databases/backends/asyncmy.py
databases/backends/mysql.py
databases/backends/postgres.py
databases/backends/sqlite.py
databases-0.8.0.dist-info/LICENSE.md
databases-0.8.0.dist-info/METADATA
databases-0.8.0.dist-info/WHEEL
databases-0.8.0.dist-info/top_level.txt
databases-0.8.0.dist-info/RECORD
