Metadata-Version: 2.1
Name: databases
Version: 0.8.0
Summary: Async database support for Python.
Home-page: https://github.com/encode/databases
Author: Tom Christie
Author-email: tom@tomchristie.com
License: BSD
Platform: UNKNOWN
Classifier: Development Status :: 3 - Alpha
Classifier: Environment :: Web Environment
Classifier: Intended Audience :: Developers
Classifier: License :: OSI Approved :: BSD License
Classifier: Operating System :: OS Independent
Classifier: Topic :: Internet :: WWW/HTTP
Classifier: Programming Language :: Python :: 3
Classifier: Programming Language :: Python :: 3.7
Classifier: Programming Language :: Python :: 3.8
Classifier: Programming Language :: Python :: 3.9
Classifier: Programming Language :: Python :: 3.10
Classifier: Programming Language :: Python :: 3 :: Only
Requires-Python: >=3.7
Provides-Extra: postgresql
Provides-Extra: asyncpg
Provides-Extra: aiopg
Provides-Extra: mysql
Provides-Extra: aiomysql
Provides-Extra: asyncmy
Provides-Extra: sqlite
Provides-Extra: aiosqlite
